jumpDB/__init__.py
jumpDB/jump_db.py
tests/__init__.py
tests/conftest.py
tests/test_db.py
tests/test_segment.py
jumpDB-0.0.6.dist-info/LICENSE
jumpDB-0.0.6.dist-info/METADATA
jumpDB-0.0.6.dist-info/WHEEL
jumpDB-0.0.6.dist-info/top_level.txt
jumpDB-0.0.6.dist-info/RECORD
