Metadata-Version: 2.1
Name: jumpDB
Version: 0.0.6
Summary: A simple kv store 
Home-page: https://github.com/NavyaZaveri/jumpDB
Author: Navya Zaveri
Author-email: author@example.com
License: UNKNOWN
Platform: UNKNOWN
Classifier: Programming Language :: Python :: 3
Classifier: Operating System :: OS Independent
Requires-Python: >=3.6
Requires-Dist: attrs (==19.3.0)
Requires-Dist: Babel (==2.8.0)
Requires-Dist: bitarray (==1.2.1)
Requires-Dist: certifi (==2019.11.28)
Requires-Dist: chardet (==3.0.4)
Requires-Dist: docutils (==0.16)
Requires-Dist: idna (==2.8)
Requires-Dist: imagesize (==1.2.0)
Requires-Dist: importlib-metadata (==1.4.0)
Requires-Dist: Jinja2 (==2.10.3)
Requires-Dist: MarkupSafe (==1.1.1)
Requires-Dist: more-itertools (==8.1.0)
Requires-Dist: packaging (==20.0)
Requires-Dist: pluggy (==0.13.1)
Requires-Dist: py (==1.8.1)
Requires-Dist: pybloom-live (==3.0.0)
Requires-Dist: Pygments (==2.5.2)
Requires-Dist: pyparsing (==2.4.6)
Requires-Dist: pytest (==5.3.3)
Requires-Dist: pytz (==2019.3)
Requires-Dist: recommonmark (==0.6.0)
Requires-Dist: requests (==2.22.0)
Requires-Dist: six (==1.14.0)
Requires-Dist: snowballstemmer (==2.0.0)
Requires-Dist: sortedcontainers (==2.1.0)
Requires-Dist: urllib3 (==1.25.8)
Requires-Dist: wcwidth (==0.1.8)
Requires-Dist: zipp (==1.0.0)
